test_timer/__init__.py
test_timer/base.py
test_timer-0.0.2.dist-info/WHEEL
test_timer-0.0.2.dist-info/METADATA
test_timer-0.0.2.dist-info/RECORD
