Metadata-Version: 2.1
Name: test-timer
Version: 0.0.2
Summary: Benchmark your code while unit testing them
Home-page: https://github.com/mnislam01/test_timer
License: MIT
Keywords: unitest,bechmark,test_timer,time_a_function,time_and_test
Author: nazrul
Author-email: mnazrul.c@gmail.com
Maintainer: nazrul
Maintainer-email: mnazrul.c@gmail.com
Requires-Python: >=3.8,<4.0
Classifier: License :: OSI Approved :: MIT License
Classifier: Programming Language :: Python :: 3
Classifier: Programming Language :: Python :: 3.10
Classifier: Programming Language :: Python :: 3.8
Classifier: Programming Language :: Python :: 3.9
Project-URL: Documentation, https://github.com/mnislam01/test_timer#readme
Project-URL: Repository, https://github.com/mnislam01/test_timer
